{
  "$schema": "https://developer.microsoft.com/json-schemas/fabric/item/report/definition/visualContainer/2.3.0/schema.json",
  "name": "415d17e8928bf8526ad3",
  "position": {
    "x": 864.06438631790741,
    "y": 159.67806841046277,
    "z": 5007,
    "height": 521.52917505030177,
    "width": 399.19517102615691,
    "tabOrder": 5005
  },
  "visual": {
    "visualType": "map",
    "query": {
      "queryState": {
        "Series": {
          "projections": [
            {
              "field": {
                "Column": {
                  "Expression": {
                    "SourceRef": {
                      "Entity": "dHora"
                    }
                  },
                  "Property": "Período"
                }
              },
              "queryRef": "dHora.Período",
              "nativeQueryRef": "Período"
            }
          ]
        },
        "Size": {
          "projections": [
            {
              "field": {
                "Measure": {
                  "Expression": {
                    "SourceRef": {
                      "Entity": "Medidas"
                    }
                  },
                  "Property": "Total Ocorrências"
                }
              },
              "queryRef": "Medidas.Total Ocorrências",
              "nativeQueryRef": "Total Ocorrências"
            }
          ]
        },
        "Tooltips": {
          "projections": [
            {
              "field": {
                "Aggregation": {
                  "Expression": {
                    "Column": {
                      "Expression": {
                        "SourceRef": {
                          "Entity": "fOcorrencias"
                        }
                      },
                      "Property": "Endereco"
                    }
                  },
                  "Function": 3
                }
              },
              "queryRef": "Min(fOcorrencias.Endereco)",
              "nativeQueryRef": "Endereco"
            },
            {
              "field": {
                "Aggregation": {
                  "Expression": {
                    "Column": {
                      "Expression": {
                        "SourceRef": {
                          "Entity": "fOcorrencias"
                        }
                      },
                      "Property": "Motivo"
                    }
                  },
                  "Function": 3
                }
              },
              "queryRef": "Min(fOcorrencias.Motivo)",
              "nativeQueryRef": "Primeiro Motivo"
            }
          ]
        },
        "X": {
          "projections": [
            {
              "field": {
                "Column": {
                  "Expression": {
                    "SourceRef": {
                      "Entity": "fOcorrencias"
                    }
                  },
                  "Property": "Longitude"
                }
              },
              "queryRef": "Min(fOcorrencias.Longitude)",
              "nativeQueryRef": "Longitude"
            }
          ]
        },
        "Y": {
          "projections": [
            {
              "field": {
                "Column": {
                  "Expression": {
                    "SourceRef": {
                      "Entity": "fOcorrencias"
                    }
                  },
                  "Property": "Latitude"
                }
              },
              "queryRef": "Min(fOcorrencias.Latitude)",
              "nativeQueryRef": "Latitude"
            }
          ]
        }
      }
    },
    "objects": {
      "mapControls": [
        {
          "properties": {
            "autoZoom": {
              "expr": {
                "Literal": {
                  "Value": "true"
                }
              }
            }
          }
        }
      ],
      "categoryLabels": [
        {
          "properties": {
            "show": {
              "expr": {
                "Literal": {
                  "Value": "false"
                }
              }
            },
            "enableBackground": {
              "expr": {
                "Literal": {
                  "Value": "true"
                }
              }
            }
          }
        }
      ],
      "dataPoint": [
        {
          "properties": {
            "fill": {
              "solid": {
                "color": {
                  "expr": {
                    "ThemeDataColor": {
                      "ColorId": 4,
                      "Percent": 0
                    }
                  }
                }
              }
            }
          }
        },
        {
          "properties": {
            "fill": {
              "solid": {
                "color": {
                  "expr": {
                    "ThemeDataColor": {
                      "ColorId": 4,
                      "Percent": 0
                    }
                  }
                }
              }
            }
          },
          "selector": {
            "data": [
              {
                "scopeId": {
                  "Comparison": {
                    "ComparisonKind": 0,
                    "Left": {
                      "Column": {
                        "Expression": {
                          "SourceRef": {
                            "Entity": "dHora"
                          }
                        },
                        "Property": "Período"
                      }
                    },
                    "Right": {
                      "Literal": {
                        "Value": "'Manhã'"
                      }
                    }
                  }
                }
              }
            ]
          }
        },
        {
          "properties": {
            "fill": {
              "solid": {
                "color": {
                  "expr": {
                    "ThemeDataColor": {
                      "ColorId": 2,
                      "Percent": 0
                    }
                  }
                }
              }
            }
          },
          "selector": {
            "data": [
              {
                "scopeId": {
                  "Comparison": {
                    "ComparisonKind": 0,
                    "Left": {
                      "Column": {
                        "Expression": {
                          "SourceRef": {
                            "Entity": "dHora"
                          }
                        },
                        "Property": "Período"
                      }
                    },
                    "Right": {
                      "Literal": {
                        "Value": "'Noite'"
                      }
                    }
                  }
                }
              }
            ]
          }
        },
        {
          "properties": {
            "fill": {
              "solid": {
                "color": {
                  "expr": {
                    "ThemeDataColor": {
                      "ColorId": 9,
                      "Percent": 0
                    }
                  }
                }
              }
            }
          },
          "selector": {
            "data": [
              {
                "scopeId": {
                  "Comparison": {
                    "ComparisonKind": 0,
                    "Left": {
                      "Column": {
                        "Expression": {
                          "SourceRef": {
                            "Entity": "dHora"
                          }
                        },
                        "Property": "Período"
                      }
                    },
                    "Right": {
                      "Literal": {
                        "Value": "'Tarde'"
                      }
                    }
                  }
                }
              }
            ]
          }
        }
      ],
      "bubbles": [
        {
          "properties": {
            "markerRangeType": {
              "expr": {
                "Literal": {
                  "Value": "'auto'"
                }
              }
            },
            "bubbleSize": {
              "expr": {
                "Literal": {
                  "Value": "1L"
                }
              }
            }
          }
        }
      ],
      "mapStyles": [
        {
          "properties": {
            "mapTheme": {
              "expr": {
                "Literal": {
                  "Value": "'canvasLight'"
                }
              }
            }
          }
        }
      ]
    },
    "visualContainerObjects": {
      "title": [
        {
          "properties": {
            "show": {
              "expr": {
                "Literal": {
                  "Value": "true"
                }
              }
            },
            "text": {
              "expr": {
                "Literal": {
                  "Value": "'Ocorrências'"
                }
              }
            },
            "fontFamily": {
              "expr": {
                "Literal": {
                  "Value": "'''Segoe UI'', wf_segoe-ui_normal, helvetica, arial, sans-serif'"
                }
              }
            }
          }
        }
      ],
      "background": [
        {
          "properties": {
            "show": {
              "expr": {
                "Literal": {
                  "Value": "false"
                }
              }
            }
          }
        }
      ],
      "border": [
        {
          "properties": {
            "show": {
              "expr": {
                "Literal": {
                  "Value": "false"
                }
              }
            }
          }
        }
      ]
    },
    "drillFilterOtherVisuals": true
  },
  "filterConfig": {
    "filters": [
      {
        "name": "0a7c43186f8f9d898a2b",
        "field": {
          "Column": {
            "Expression": {
              "SourceRef": {
                "Entity": "dHora"
              }
            },
            "Property": "Período"
          }
        },
        "type": "Categorical"
      },
      {
        "name": "ed3315f6524f4a102d49",
        "field": {
          "Measure": {
            "Expression": {
              "SourceRef": {
                "Entity": "Medidas"
              }
            },
            "Property": "Total Ocorrências"
          }
        },
        "type": "Advanced"
      },
      {
        "name": "d429348fe9835b0aaa9d",
        "field": {
          "Aggregation": {
            "Expression": {
              "Column": {
                "Expression": {
                  "SourceRef": {
                    "Entity": "fOcorrencias"
                  }
                },
                "Property": "Endereco"
              }
            },
            "Function": 3
          }
        },
        "type": "Advanced"
      },
      {
        "name": "29a26e40edaacddd5156",
        "field": {
          "Aggregation": {
            "Expression": {
              "Column": {
                "Expression": {
                  "SourceRef": {
                    "Entity": "fOcorrencias"
                  }
                },
                "Property": "Motivo"
              }
            },
            "Function": 3
          }
        },
        "type": "Advanced"
      },
      {
        "name": "4b74b8bf67e4e6e2e28c",
        "field": {
          "Column": {
            "Expression": {
              "SourceRef": {
                "Entity": "fOcorrencias"
              }
            },
            "Property": "Latitude"
          }
        },
        "type": "Categorical"
      },
      {
        "name": "6bf0ffb1c68d149d8f41",
        "field": {
          "Column": {
            "Expression": {
              "SourceRef": {
                "Entity": "fOcorrencias"
              }
            },
            "Property": "Longitude"
          }
        },
        "type": "Categorical"
      }
    ]
  }
}